{
    "任务": {
        "next": [
            "一键领取",
            "打开任务",
            "返回主菜单"
        ]
    },
    "一键领取": {
        "recognition": "OCR",
        "roi": [
            14,
            605,
            156,
            120
        ],
        "expected": [
            "一键领取",
            "键领取"
        ],
        "action": "Click",
        "next": [
            "关闭奖励通知",
            "任务"
        ]
    },
    "打开任务": {
        "recognition": "OCR",
        "roi": [
            927,
            178,
            128,
            116
        ],
        "expected": "任务",
        "action": "Click",
        "next": [
            "切换到日常任务"
        ]
    },
    "切换到日常任务": {
        "recognition": "OCR",
        "roi": [
            0,
            29,
            177,
            130
        ],
        "expected": [
            "日常",
            "24日常"
        ],
        "action": "Click",
        "next": [
            "任务"
        ]
    },
    "活动任务": {
        "next": [
            "一键领取活动任务",
            "打开活动任务",
            "打开活动战斗",
            "返回主菜单"
        ]
    },
    "一键领取活动任务": {
        "recognition": "OCR",
        "roi": [
            14,
            605,
            156,
            120
        ],
        "expected": [
            "一键领取",
            "键领取"
        ],
        "action": "Click",
        "next": [
            "关闭奖励通知",
            "活动任务"
        ]
    },
    "打开活动任务": {
        "is_sub": true,
        "recognition": "OCR",
        "roi": [
            200,
            633,
            150,
            138
        ],
        "expected": [
            "任务",
            "云中行走"
        ],
        "action": "Click"
    }
}